haystack_integrations/components/common/py.typed
haystack_integrations/components/common/google_genai/__init__.py
haystack_integrations/components/common/google_genai/utils.py
haystack_integrations/components/embedders/py.typed
haystack_integrations/components/embedders/google_genai/__init__.py
haystack_integrations/components/embedders/google_genai/document_embedder.py
haystack_integrations/components/embedders/google_genai/text_embedder.py
haystack_integrations/components/generators/py.typed
haystack_integrations/components/generators/google_genai/__init__.py
haystack_integrations/components/generators/google_genai/chat/chat_generator.py
haystack_integrations/components/generators/google_genai/chat/utils.py
google_genai_haystack-3.2.0.dist-info/METADATA
google_genai_haystack-3.2.0.dist-info/WHEEL
google_genai_haystack-3.2.0.dist-info/licenses/LICENSE.txt
google_genai_haystack-3.2.0.dist-info/RECORD
