Metadata-Version: 2.4
Name: google-genai-haystack
Version: 3.2.0
Summary: Use models like Gemini via Google Gen AI SDK
Project-URL: Documentation, https://github.com/deepset-ai/haystack-core-integrations/tree/main/integrations/google_genai#readme
Project-URL: Issues, https://github.com/deepset-ai/haystack-core-integrations/issues
Project-URL: Source, https://github.com/deepset-ai/haystack-core-integrations/tree/main/integrations/google_genai
Author-email: deepset GmbH <info@deepset.ai>, Gary Badwal <gurpreet071999@gmail.com>
License-Expression: Apache-2.0
License-File: LICENSE.txt
Classifier: Development Status :: 4 - Beta
Classifier: License :: OSI Approved :: Apache Software License
Classifier: Programming Language :: Python
Classifier: Programming Language :: Python :: 3.10
Classifier: Programming Language :: Python :: 3.11
Classifier: Programming Language :: Python :: 3.12
Classifier: Programming Language :: Python :: 3.13
Classifier: Programming Language :: Python :: Implementation :: CPython
Classifier: Programming Language :: Python :: Implementation :: PyPy
Requires-Python: >=3.10
Requires-Dist: google-genai[aiohttp]>=1.51.0
Requires-Dist: haystack-ai>=2.22.0
Requires-Dist: jsonref>=1.0.0
